skweak/__init__.py
skweak/aggregation.py
skweak/analysis.py
skweak/base.py
skweak/doclevel.py
skweak/gazetteers.py
skweak/generative.py
skweak/heuristics.py
skweak/spacy.py
skweak/utils.py
skweak/voting.py
skweak-0.3.3.dist-info/LICENSE.txt
skweak-0.3.3.dist-info/METADATA
skweak-0.3.3.dist-info/WHEEL
skweak-0.3.3.dist-info/top_level.txt
skweak-0.3.3.dist-info/RECORD
