Metadata-Version: 2.1
Name: skweak
Version: 0.3.3
Summary: Software toolkit for weak supervision in NLP
Home-page: https://github.com/NorskRegnesentral/skweak
Author: Pierre Lison
Author-email: plison@nr.no
License: LICENSE.txt
Classifier: Programming Language :: Python :: 3
Classifier: Programming Language :: Python :: 3.7
Classifier: License :: OSI Approved :: MIT License
Classifier: Operating System :: OS Independent
Classifier: Intended Audience :: Developers
Classifier: Intended Audience :: Science/Research
Classifier: Topic :: Scientific/Engineering
Requires-Python: >=3.7.4
License-File: LICENSE.txt
Requires-Dist: spacy (>=3.0)
Requires-Dist: hmmlearn (>=0.3.0)
Requires-Dist: pandas (>=0.23)
Requires-Dist: numpy (>=1.18)
